marius_s_mod1_atsiskaitymas/__init__.py
marius_s_mod1_atsiskaitymas/articles.csv
marius_s_mod1_atsiskaitymas/crawler.py
marius_s_mod1_atsiskaitymas-0.5.dist-info/METADATA
marius_s_mod1_atsiskaitymas-0.5.dist-info/WHEEL
marius_s_mod1_atsiskaitymas-0.5.dist-info/RECORD
