Metadata-Version: 2.1
Name: marius-s-mod1-atsiskaitymas
Version: 0.5
Summary: A crawler for news articles from specified websites
Author: Marelis272
Author-email: Mariusstosk@gmail.com
Requires-Python: >=3.13,<4.0
Classifier: Programming Language :: Python :: 3
Classifier: Programming Language :: Python :: 3.13
Requires-Dist: lxml (>=5.3.0,<6.0.0)
Requires-Dist: requests (>=2.32.3,<3.0.0)
